sql_manager/__init__.py
sql_manager/core/__init__.py
sql_manager/core/manager.py
sql_manager/core/model.py
sql_manager/version/version.json
sql_manager-1.0.5.dist-info/METADATA
sql_manager-1.0.5.dist-info/WHEEL
sql_manager-1.0.5.dist-info/top_level.txt
sql_manager-1.0.5.dist-info/RECORD
