Metadata-Version: 2.1
Name: sql_manager
Version: 1.0.5
Summary: A simple database manager with sqlalchemy
Home-page: https://github.com/suqingdong/sql_manager
Author: suqingdong
Author-email: suqingdong1114@gmail.com
License: BSD License
Project-URL: Documentation, https://sql_manager.readthedocs.io
Project-URL: Tracker, https://github.com/suqingdong/sql_manager/issues
Platform: UNKNOWN
Classifier: Development Status :: 5 - Production/Stable
Classifier: Operating System :: OS Independent
Classifier: Intended Audience :: Developers
Classifier: License :: OSI Approved :: BSD License
Classifier: Programming Language :: Python
Classifier: Programming Language :: Python :: 3
Classifier: Programming Language :: Python :: 3.8
Classifier: Topic :: Software Development :: Libraries
